CHANGELOG.md
LICENSE
MANIFEST.in
README.md
setup.py
cythonpowered/__init__.py
cythonpowered.egg-info/PKG-INFO
cythonpowered.egg-info/SOURCES.txt
cythonpowered.egg-info/dependency_links.txt
cythonpowered.egg-info/entry_points.txt
cythonpowered.egg-info/requires.txt
cythonpowered.egg-info/top_level.txt
cythonpowered/random/__init__.py
cythonpowered/random/random.c
cythonpowered/random/random.pyx
tests/test_random.py
utils/__init__.py
utils/main.py
utils/benchmark/__init__.py
utils/benchmark/_base.py
utils/benchmark/_random.py
utils/benchmark/benchmark_runner.py
utils/definitions/__init__.py
utils/definitions/_base.py
utils/definitions/_random.py
utils/definitions/list_functions.py