Metadata-Version: 2.1
Name: cythonpowered
Version: 0.1.10
Summary: Cython-powered replacements for popular Python functions. And more.
Home-page: https://github.com/lucian-croitoru/cythonpowered
Author: Lucian Croitoru
Author-email: lucianalexandru.croitoru@gmail.com
License: GNU GPLv3
Keywords: python,cython,random,performance
Classifier: Development Status :: 2 - Pre-Alpha
Classifier: Intended Audience :: Developers
Classifier: Operating System :: MacOS
Classifier: Operating System :: POSIX
Classifier: Operating System :: POSIX :: Linux
Classifier: Operating System :: Unix
Classifier: Programming Language :: Python :: 3
Classifier: Programming Language :: Python :: 3.8
Classifier: Programming Language :: Python :: 3.9
Classifier: Programming Language :: Python :: 3.10
Classifier: Programming Language :: Python :: 3.11
Classifier: Programming Language :: Python :: 3 :: Only
Classifier: Topic :: Software Development :: Libraries :: Python Modules
License-File: LICENSE
Requires-Dist: setuptools==74.1.3
Requires-Dist: wheel==0.43.0
Requires-Dist: Cython>=3.0.0
Requires-Dist: packaging==24.0
Requires-Dist: more-itertools==10.0.0
Requires-Dist: jaraco.functools>=4.0.0
Requires-Dist: jaraco.text>=4.0.0
Requires-Dist: psutil>=6.0.0
Requires-Dist: py-cpuinfo>=9.0.0
Requires-Dist: prettytable>=3.0.0
